{
  "Active": true,
  "Age": 23,
  "AverageDraftPosition": null,
  "BirthDate": "/Date(646113600000-0400)/",
  "BirthDateString": "June 23, 1990",
  "ByeWeek": 9,
  "College": "Virginia Tech",
  "CollegeDraftPick": 199,
  "CollegeDraftRound": 6,
  "CollegeDraftTeam": null,
  "CollegeDraftYear": 2013,
  "CurrentTeam": "DET",
  "DepthDisplayOrder": null,
  "DepthOrder": null,
  "DepthPosition": null,
  "DepthPositionCategory": null,
  "Experience": 0,
  "ExperienceString": "Rookie",
  "FantasyPosition": "WR",
  "FirstName": "Corey",
  "Height": "6'2\"",
  "HeightFeet": 6,
  "HeightInches": 2,
  "InjuryStatus": null,
  "IsUndraftedFreeAgent": false,
  "LastName": "Fuller",
  "LatestNews": [

  ],
  "Name": "Corey Fuller",
  "Number": 10,
  "PhotoUrl": "http://static.nfldata.com/images/player/15123.jpg",
  "PlayerID": 15123,
  "PlayerSeason": null,
  "Position": "WR",
  "PositionCategory": "OFF",
  "ShortName": "C.Fuller",
  "Status": "Injured Reserve",
  "Team": "DET",
  "UpcomingGameOpponent": null,
  "UpcomingGameWeek": 0,
  "Weight": "204"
}