{
  "Active": false,
  "Age": 27,
  "AverageDraftPosition": 138.1,
  "BirthDate": "/Date(516600000000-0400)/",
  "BirthDateString": "May 16, 1986",
  "ByeWeek": null,
  "College": "Oklahoma",
  "CollegeDraftPick": null,
  "CollegeDraftRound": null,
  "CollegeDraftTeam": null,
  "CollegeDraftYear": 2008,
  "CurrentTeam": null,
  "DepthDisplayOrder": 23,
  "DepthOrder": 0,
  "DepthPosition": "K",
  "DepthPositionCategory": "ST",
  "Experience": 5,
  "ExperienceString": "5th Season",
  "FantasyPosition": "K",
  "FirstName": "Garrett",
  "Height": "5'8\"",
  "HeightFeet": 5,
  "HeightInches": 8,
  "InjuryStatus": null,
  "IsUndraftedFreeAgent": true,
  "LastName": "Hartley",
  "LatestNews": [
    {
      "Content": "Saints waived K Garrett Hartley.",
      "NewsID": 8869,
      "PlayerID": 418,
      "Source": "NBCSports.com",
      "Team": null,
      "TermsOfUse": "NBCSports.com feeds in the RSS format are provided free of charge for use by individuals for personal, non-commercial uses. Attribution to NBCSports.com must be provided in connection with your use of the feeds. If you provide this attribution in text, please use: \"NBCSports.com\". If you provide this attribution with a graphic, please use the NBCSports.com logo that we have included in the feed itself. We reserve all rights in and to the NBCSports.com logo, and your right to use the NBCSports.com logo is limited to providing attribution in connection with these RSS feeds. By using the NBCSports.com RSS news feed, you agree to be bound by the NBCSports.com Terms and Conditions. NBCSports.com reserves the right to modify these Terms of Use and the Terms of Service referenced above from time to time and without notice. Msnbc.com reserves the right to cease offering these feeds at any time or require you to cease distributing these feeds at any time for any reason.",
      "Title": "Saints part ways with struggling K Hartley",
      "Updated": "/Date(1387320900000-0500)/",
      "Url": "http://www.rotoworld.com/player/nfl/5053/garrett-hartley"
    }
  ],
  "Name": "Garrett Hartley",
  "Number": 5,
  "PhotoUrl": "http://static.nfldata.com/images/player/418.jpg",
  "PlayerID": 418,
  "PlayerSeason": {
    "Activated": 14,
    "AssistedTackles": 0,
    "BlockedKickReturnTouchdowns": 0,
    "BlockedKickReturnYards": 0,
    "BlockedKicks": 0,
    "CustomD365FantasyPoints": 93,
    "DefensiveTouchdowns": 0,
    "ExtraPointsAttempted": 36,
    "ExtraPointsHadBlocked": 0,
    "ExtraPointsMade": 36,
    "FantasyPoints": 93.0,
    "FantasyPointsPPR": 93.0,
    "FantasyPosition": "K",
    "FieldGoalPercentage": 73.1,
    "FieldGoalReturnTouchdowns": 0,
    "FieldGoalReturnYards": 0,
    "FieldGoalsAttempted": 26,
    "FieldGoalsHadBlocked": 0,
    "FieldGoalsLongestMade": 48,
    "FieldGoalsMade": 19,
    "FumbleReturnTouchdowns": 0,
    "FumbleReturnYards": 0,
    "Fumbles": 0,
    "FumblesForced": 0,
    "FumblesLost": 0,
    "FumblesOutOfBounds": 0,
    "FumblesOwnRecoveries": 0,
    "FumblesRecovered": 0,
    "Humidity": 58,
    "InterceptionReturnTouchdowns": 0,
    "InterceptionReturnYards": 0,
    "Interceptions": 0,
    "KickReturnFairCatches": 0,
    "KickReturnLong": 0,
    "KickReturnTouchdowns": 0,
    "KickReturnYards": 0,
    "KickReturnYardsPerAttempt": 0,
    "KickReturns": 0,
    "MiscAssistedTackles": 0,
    "MiscFumblesForced": 0,
    "MiscFumblesRecovered": 0,
    "MiscSoloTackles": 0,
    "Name": "Garrett Hartley",
    "Number": 5,
    "OffensiveTouchdowns": 0,
    "PassesDefended": 0,
    "PassingAttempts": 0,
    "PassingCompletionPercentage": 0,
    "PassingCompletions": 0,
    "PassingInterceptions": 0,
    "PassingLong": 0,
    "PassingRating": 0,
    "PassingSackYards": 0,
    "PassingSacks": 0,
    "PassingTouchdowns": 0,
    "PassingYards": 0,
    "PassingYardsPerAttempt": 0,
    "PassingYardsPerCompletion": 0,
    "Played": 14,
    "PlayerID": 418,
    "PlayerSeasonID": 10361967,
    "Position": "K",
    "PositionCategory": "ST",
    "PuntAverage": 0,
    "PuntInside20": 0,
    "PuntLong": 0,
    "PuntNetAverage": 0,
    "PuntNetYards": 0,
    "PuntReturnFairCatches": 0,
    "PuntReturnLong": 0,
    "PuntReturnTouchdowns": 0,
    "PuntReturnYards": 0,
    "PuntReturnYardsPerAttempt": 0,
    "PuntReturns": 0,
    "PuntTouchbacks": 0,
    "PuntYards": 0,
    "Punts": 0,
    "PuntsHadBlocked": 0,
    "QuarterbackHits": 0,
    "ReceivingLong": 0,
    "ReceivingTargets": 0,
    "ReceivingTouchdowns": 0,
    "ReceivingYards": 0,
    "ReceivingYardsPerReception": 0,
    "ReceivingYardsPerTarget": 0,
    "ReceptionPercentage": 0,
    "Receptions": 0,
    "RushingAttempts": 0,
    "RushingLong": 0,
    "RushingTouchdowns": 0,
    "RushingYards": 0,
    "RushingYardsPerAttempt": 0,
    "SackYards": 0,
    "Sacks": 0.0,
    "Safeties": 0,
    "SafetiesAllowed": 0,
    "ScoringDetails": null,
    "Season": 2013,
    "SeasonType": 1,
    "ShortName": "G.Hartley",
    "SoloTackles": 0,
    "SpecialTeamsAssistedTackles": 0,
    "SpecialTeamsFumblesForced": 0,
    "SpecialTeamsFumblesRecovered": 0,
    "SpecialTeamsSoloTackles": 0,
    "SpecialTeamsTouchdowns": 0,
    "Started": 0,
    "Tackles": 0,
    "TacklesForLoss": 0,
    "Team": "NO",
    "Temperature": 59,
    "Touchdowns": 0,
    "TwoPointConversionPasses": 0,
    "TwoPointConversionReceptions": 0,
    "TwoPointConversionRuns": 0,
    "WindSpeed": 5
  },
  "Position": "K",
  "PositionCategory": "ST",
  "ShortName": "G.Hartley",
  "Status": "Inactive",
  "Team": "NO",
  "UpcomingGameOpponent": null,
  "UpcomingGameWeek": 0,
  "Weight": "196"
}