{
  "Active": true,
  "Age": 27,
  "AverageDraftPosition": null,
  "BirthDate": "/Date(528955200000-0400)/",
  "BirthDateString": "October 6, 1986",
  "ByeWeek": 5,
  "College": "North Carolina",
  "CollegeDraftPick": 73,
  "CollegeDraftRound": 2,
  "CollegeDraftTeam": null,
  "CollegeDraftYear": 2009,
  "CurrentTeam": "WAS",
  "DepthDisplayOrder": 8,
  "DepthOrder": 3,
  "DepthPosition": "TE",
  "DepthPositionCategory": "OFF",
  "Experience": 5,
  "ExperienceString": "5th Season",
  "FantasyPosition": "TE",
  "FirstName": "Richard",
  "Height": "6'4\"",
  "HeightFeet": 6,
  "HeightInches": 4,
  "InjuryStatus": null,
  "IsUndraftedFreeAgent": false,
  "LastName": "Quinn",
  "LatestNews": [

  ],
  "Name": "Richard Quinn",
  "Number": 47,
  "PhotoUrl": "http://static.nfldata.com/images/player/8708.jpg",
  "PlayerID": 8708,
  "PlayerSeason": null,
  "Position": "TE",
  "PositionCategory": "OFF",
  "ShortName": "R.Quinn",
  "Status": "Injured Reserve",
  "Team": "WAS",
  "UpcomingGameOpponent": null,
  "UpcomingGameWeek": 0,
  "Weight": "258"
}